helperBy/__init__.py
helperBy/analogs.py
helperBy/buildCustom.py
helperBy/core.py
helperBy/progress.py
helperBy/system_info.py
helperBy/utils.py
helperby-0.1.5.dist-info/licenses/LICENSE
helperby-0.1.5.dist-info/METADATA
helperby-0.1.5.dist-info/WHEEL
helperby-0.1.5.dist-info/top_level.txt
helperby-0.1.5.dist-info/RECORD
